{
  "draft": "3B",
  "benchmark": "OpenMMLab-Config",
  "n": 20,
  "n_errors": 0,
  "tps_avg": 51.431,
  "tps_median": 51.989999999999995,
  "tps_min": 40.34,
  "tps_max": 52.98,
  "speedup_vs_ar": 1.5627772713460955,
  "accept_rate_mean": 1.0,
  "accept_rate_median": 1.0,
  "accept_rate_p10": 1.0,
  "accept_rate_p90": 1.0,
  "low_accept_count": 0,
  "high_accept_count": 20,
  "structural_quality_score": 0.874905,
  "severe_rate": 0.0304,
  "off_structure_rate": 0.0,
  "repetition_rate": 0.00278,
  "truncation_rate": 0.186135,
  "structure_not_preserved": 0.3,
  "repair_count": 0.0,
  "guard_trigger_count": 0.0,
  "total_drafted": 128.0,
  "total_accepted": 128.0,
  "peak_memory_mb": 8.125,
  "per_sample": [
    {
      "sample_idx": 0,
      "tps": 40.34,
      "wall_time": 3.3660426139831543,
      "accept_rate": 1.0,
      "repair_count": 0,
      "guard_trigger_count": 0,
      "total_drafted": 128,
      "total_accepted": 128,
      "tokens_generated": 128,
      "structural_quality_score": 0.6667,
      "severe_rate": 0.0667,
      "off_structure_rate": 0.0,
      "repetition_rate": 0.0,
      "truncation_rate": 0.2,
      "structure_not_preserved": 1.0
    },
    {
      "sample_idx": 1,
      "tps": 51.87,
      "wall_time": 2.6664414405822754,
      "accept_rate": 1.0,
      "repair_count": 0,
      "guard_trigger_count": 0,
      "total_drafted": 128,
      "total_accepted": 128,
      "tokens_generated": 128,
      "structural_quality_score": 0.925,
      "severe_rate": 0.0,
      "off_structure_rate": 0.0,
      "repetition_rate": 0.0,
      "truncation_rate": 0.25,
      "structure_not_preserved": 0.0
    },
    {
      "sample_idx": 2,
      "tps": 51.97,
      "wall_time": 2.672513961791992,
      "accept_rate": 1.0,
      "repair_count": 0,
      "guard_trigger_count": 0,
      "total_drafted": 128,
      "total_accepted": 128,
      "tokens_generated": 128,
      "structural_quality_score": 0.6667,
      "severe_rate": 0.0667,
      "off_structure_rate": 0.0,
      "repetition_rate": 0.0,
      "truncation_rate": 0.2,
      "structure_not_preserved": 1.0
    },
    {
      "sample_idx": 3,
      "tps": 52.12,
      "wall_time": 2.6888582706451416,
      "accept_rate": 1.0,
      "repair_count": 0,
      "guard_trigger_count": 0,
      "total_drafted": 128,
      "total_accepted": 128,
      "tokens_generated": 128,
      "structural_quality_score": 0.9688,
      "severe_rate": 0.0,
      "off_structure_rate": 0.0,
      "repetition_rate": 0.0,
      "truncation_rate": 0.3125,
      "structure_not_preserved": 0.0
    },
    {
      "sample_idx": 4,
      "tps": 51.5,
      "wall_time": 2.6905126571655273,
      "accept_rate": 1.0,
      "repair_count": 0,
      "guard_trigger_count": 0,
      "total_drafted": 128,
      "total_accepted": 128,
      "tokens_generated": 128,
      "structural_quality_score": 0.7357,
      "severe_rate": 0.0476,
      "off_structure_rate": 0.0,
      "repetition_rate": 0.0,
      "truncation_rate": 0.0476,
      "structure_not_preserved": 1.0
    },
    {
      "sample_idx": 5,
      "tps": 52.23,
      "wall_time": 2.659505844116211,
      "accept_rate": 1.0,
      "repair_count": 0,
      "guard_trigger_count": 0,
      "total_drafted": 128,
      "total_accepted": 128,
      "tokens_generated": 128,
      "structural_quality_score": 0.925,
      "severe_rate": 0.0,
      "off_structure_rate": 0.0,
      "repetition_rate": 0.0,
      "truncation_rate": 0.25,
      "structure_not_preserved": 0.0
    },
    {
      "sample_idx": 6,
      "tps": 52.17,
      "wall_time": 2.6569020748138428,
      "accept_rate": 1.0,
      "repair_count": 0,
      "guard_trigger_count": 0,
      "total_drafted": 128,
      "total_accepted": 128,
      "tokens_generated": 128,
      "structural_quality_score": 0.9818,
      "severe_rate": 0.0,
      "off_structure_rate": 0.0,
      "repetition_rate": 0.0,
      "truncation_rate": 0.1818,
      "structure_not_preserved": 0.0
    },
    {
      "sample_idx": 7,
      "tps": 52.59,
      "wall_time": 2.6485064029693604,
      "accept_rate": 1.0,
      "repair_count": 0,
      "guard_trigger_count": 0,
      "total_drafted": 128,
      "total_accepted": 128,
      "tokens_generated": 128,
      "structural_quality_score": 0.6667,
      "severe_rate": 0.0667,
      "off_structure_rate": 0.0,
      "repetition_rate": 0.0,
      "truncation_rate": 0.2,
      "structure_not_preserved": 1.0
    },
    {
      "sample_idx": 8,
      "tps": 52.68,
      "wall_time": 2.6322755813598633,
      "accept_rate": 1.0,
      "repair_count": 0,
      "guard_trigger_count": 0,
      "total_drafted": 128,
      "total_accepted": 128,
      "tokens_generated": 128,
      "structural_quality_score": 0.9824,
      "severe_rate": 0.0,
      "off_structure_rate": 0.0,
      "repetition_rate": 0.0,
      "truncation_rate": 0.1765,
      "structure_not_preserved": 0.0
    },
    {
      "sample_idx": 9,
      "tps": 52.95,
      "wall_time": 2.6443731784820557,
      "accept_rate": 1.0,
      "repair_count": 0,
      "guard_trigger_count": 0,
      "total_drafted": 128,
      "total_accepted": 128,
      "tokens_generated": 128,
      "structural_quality_score": 0.9688,
      "severe_rate": 0.0,
      "off_structure_rate": 0.0,
      "repetition_rate": 0.0,
      "truncation_rate": 0.3125,
      "structure_not_preserved": 0.0
    },
    {
      "sample_idx": 10,
      "tps": 51.77,
      "wall_time": 2.6857900619506836,
      "accept_rate": 1.0,
      "repair_count": 0,
      "guard_trigger_count": 0,
      "total_drafted": 128,
      "total_accepted": 128,
      "tokens_generated": 128,
      "structural_quality_score": 0.9818,
      "severe_rate": 0.0,
      "off_structure_rate": 0.0,
      "repetition_rate": 0.0,
      "truncation_rate": 0.1818,
      "structure_not_preserved": 0.0
    },
    {
      "sample_idx": 11,
      "tps": 52.01,
      "wall_time": 2.6662557125091553,
      "accept_rate": 1.0,
      "repair_count": 0,
      "guard_trigger_count": 0,
      "total_drafted": 128,
      "total_accepted": 128,
      "tokens_generated": 128,
      "structural_quality_score": 0.6667,
      "severe_rate": 0.0667,
      "off_structure_rate": 0.0,
      "repetition_rate": 0.0,
      "truncation_rate": 0.2,
      "structure_not_preserved": 1.0
    },
    {
      "sample_idx": 12,
      "tps": 52.06,
      "wall_time": 2.665231466293335,
      "accept_rate": 1.0,
      "repair_count": 0,
      "guard_trigger_count": 0,
      "total_drafted": 128,
      "total_accepted": 128,
      "tokens_generated": 128,
      "structural_quality_score": 0.9824,
      "severe_rate": 0.0,
      "off_structure_rate": 0.0,
      "repetition_rate": 0.0,
      "truncation_rate": 0.1765,
      "structure_not_preserved": 0.0
    },
    {
      "sample_idx": 13,
      "tps": 52.98,
      "wall_time": 2.6408958435058594,
      "accept_rate": 1.0,
      "repair_count": 0,
      "guard_trigger_count": 0,
      "total_drafted": 128,
      "total_accepted": 128,
      "tokens_generated": 128,
      "structural_quality_score": 0.9688,
      "severe_rate": 0.0,
      "off_structure_rate": 0.0,
      "repetition_rate": 0.0,
      "truncation_rate": 0.3125,
      "structure_not_preserved": 0.0
    },
    {
      "sample_idx": 14,
      "tps": 51.12,
      "wall_time": 2.7026379108428955,
      "accept_rate": 1.0,
      "repair_count": 0,
      "guard_trigger_count": 0,
      "total_drafted": 128,
      "total_accepted": 128,
      "tokens_generated": 128,
      "structural_quality_score": 1.0,
      "severe_rate": 0.0,
      "off_structure_rate": 0.0,
      "repetition_rate": 0.0,
      "truncation_rate": 0.0,
      "structure_not_preserved": 0.0
    },
    {
      "sample_idx": 15,
      "tps": 51.25,
      "wall_time": 2.744380474090576,
      "accept_rate": 1.0,
      "repair_count": 0,
      "guard_trigger_count": 0,
      "total_drafted": 128,
      "total_accepted": 128,
      "tokens_generated": 128,
      "structural_quality_score": 0.925,
      "severe_rate": 0.0,
      "off_structure_rate": 0.0,
      "repetition_rate": 0.0,
      "truncation_rate": 0.25,
      "structure_not_preserved": 0.0
    },
    {
      "sample_idx": 16,
      "tps": 52.02,
      "wall_time": 2.6625096797943115,
      "accept_rate": 1.0,
      "repair_count": 0,
      "guard_trigger_count": 0,
      "total_drafted": 128,
      "total_accepted": 128,
      "tokens_generated": 128,
      "structural_quality_score": 0.73,
      "severe_rate": 0.05,
      "off_structure_rate": 0.0,
      "repetition_rate": 0.0,
      "truncation_rate": 0.1,
      "structure_not_preserved": 1.0
    },
    {
      "sample_idx": 17,
      "tps": 51.75,
      "wall_time": 2.6766955852508545,
      "accept_rate": 1.0,
      "repair_count": 0,
      "guard_trigger_count": 0,
      "total_drafted": 128,
      "total_accepted": 128,
      "tokens_generated": 128,
      "structural_quality_score": 0.8769,
      "severe_rate": 0.0769,
      "off_structure_rate": 0.0,
      "repetition_rate": 0.0,
      "truncation_rate": 0.0769,
      "structure_not_preserved": 0.0
    },
    {
      "sample_idx": 18,
      "tps": 51.94,
      "wall_time": 2.680396795272827,
      "accept_rate": 1.0,
      "repair_count": 0,
      "guard_trigger_count": 0,
      "total_drafted": 128,
      "total_accepted": 128,
      "tokens_generated": 128,
      "structural_quality_score": 0.9083,
      "severe_rate": 0.1667,
      "off_structure_rate": 0.0,
      "repetition_rate": 0.0556,
      "truncation_rate": 0.0,
      "structure_not_preserved": 0.0
    },
    {
      "sample_idx": 19,
      "tps": 51.3,
      "wall_time": 2.706195592880249,
      "accept_rate": 1.0,
      "repair_count": 0,
      "guard_trigger_count": 0,
      "total_drafted": 128,
      "total_accepted": 128,
      "tokens_generated": 128,
      "structural_quality_score": 0.9706,
      "severe_rate": 0.0,
      "off_structure_rate": 0.0,
      "repetition_rate": 0.0,
      "truncation_rate": 0.2941,
      "structure_not_preserved": 0.0
    }
  ]
}