{
  "fly_missing": [
    {
      "blind_id": "BRV-025E4127",
      "benchmark": "argparse",
      "sample_name": "argparse_real_005",
      "sample_idx": 4
    },
    {
      "blind_id": "BRV-0690E70E",
      "benchmark": "argparse",
      "sample_name": "argparse_real_009",
      "sample_idx": 8
    },
    {
      "blind_id": "BRV-0A2F9E20",
      "benchmark": "argparse",
      "sample_name": "argparse_real_017",
      "sample_idx": 16
    },
    {
      "blind_id": "BRV-0D4903CB",
      "benchmark": "argparse",
      "sample_name": "argparse_real_018",
      "sample_idx": 17
    },
    {
      "blind_id": "BRV-1093C2F8",
      "benchmark": "argparse",
      "sample_name": "argparse_real_039",
      "sample_idx": 38
    },
    {
      "blind_id": "BRV-12C75780",
      "benchmark": "argparse",
      "sample_name": "argparse_real_043",
      "sample_idx": 42
    },
    {
      "blind_id": "BRV-18EE3DBB",
      "benchmark": "argparse",
      "sample_name": "argparse_real_046",
      "sample_idx": 45
    },
    {
      "blind_id": "BRV-1AFCD302",
      "benchmark": "argparse",
      "sample_name": "argparse_real_049",
      "sample_idx": 48
    },
    {
      "blind_id": "BRV-1E01DE75",
      "benchmark": "argparse",
      "sample_name": "argparse_real_063",
      "sample_idx": 62
    },
    {
      "blind_id": "BRV-2473CF4F",
      "benchmark": "argparse",
      "sample_name": "argparse_real_069",
      "sample_idx": 68
    },
    {
      "blind_id": "BRV-25029088",
      "benchmark": "dict_config",
      "sample_name": "dict_config_real_010",
      "sample_idx": 9
    },
    {
      "blind_id": "BRV-26B87933",
      "benchmark": "dict_config",
      "sample_name": "dict_config_real_021",
      "sample_idx": 20
    },
    {
      "blind_id": "BRV-300C65DB",
      "benchmark": "dict_config",
      "sample_name": "dict_config_real_023",
      "sample_idx": 22
    },
    {
      "blind_id": "BRV-31735784",
      "benchmark": "dict_config",
      "sample_name": "dict_config_real_027",
      "sample_idx": 26
    },
    {
      "blind_id": "BRV-34E16140",
      "benchmark": "dict_config",
      "sample_name": "dict_config_real_033",
      "sample_idx": 32
    },
    {
      "blind_id": "BRV-36969FAE",
      "benchmark": "dict_config",
      "sample_name": "dict_config_real_035",
      "sample_idx": 34
    },
    {
      "blind_id": "BRV-39F60A11",
      "benchmark": "dict_config",
      "sample_name": "dict_config_real_047",
      "sample_idx": 46
    },
    {
      "blind_id": "BRV-40F7E908",
      "benchmark": "dict_config",
      "sample_name": "dict_config_real_052",
      "sample_idx": 51
    },
    {
      "blind_id": "BRV-449DACE3",
      "benchmark": "dict_config",
      "sample_name": "dict_config_real_056",
      "sample_idx": 55
    },
    {
      "blind_id": "BRV-46461F2D",
      "benchmark": "dict_config",
      "sample_name": "dict_config_real_080",
      "sample_idx": 79
    },
    {
      "blind_id": "BRV-4A2D9370",
      "benchmark": "openmmlab_config",
      "sample_name": "openmmlab_config_real_005",
      "sample_idx": 4
    },
    {
      "blind_id": "BRV-50C782CF",
      "benchmark": "openmmlab_config",
      "sample_name": "openmmlab_config_real_006",
      "sample_idx": 5
    },
    {
      "blind_id": "BRV-580F5DFB",
      "benchmark": "openmmlab_config",
      "sample_name": "openmmlab_config_real_009",
      "sample_idx": 8
    },
    {
      "blind_id": "BRV-6283B5E7",
      "benchmark": "openmmlab_config",
      "sample_name": "openmmlab_config_real_011",
      "sample_idx": 10
    },
    {
      "blind_id": "BRV-6380EACE",
      "benchmark": "openmmlab_config",
      "sample_name": "openmmlab_config_real_015",
      "sample_idx": 14
    },
    {
      "blind_id": "BRV-66B11352",
      "benchmark": "openmmlab_config",
      "sample_name": "openmmlab_config_real_041",
      "sample_idx": 40
    },
    {
      "blind_id": "BRV-6B13FE70",
      "benchmark": "openmmlab_config",
      "sample_name": "openmmlab_config_real_044",
      "sample_idx": 43
    },
    {
      "blind_id": "BRV-6DDEC289",
      "benchmark": "openmmlab_config",
      "sample_name": "openmmlab_config_real_061",
      "sample_idx": 60
    },
    {
      "blind_id": "BRV-6EE1884A",
      "benchmark": "openmmlab_config",
      "sample_name": "openmmlab_config_real_077",
      "sample_idx": 76
    },
    {
      "blind_id": "BRV-71CBAFB0",
      "benchmark": "openmmlab_config",
      "sample_name": "openmmlab_config_real_080",
      "sample_idx": 79
    },
    {
      "blind_id": "BRV-785F35C3",
      "benchmark": "pipeline_stage_config",
      "sample_name": "pipeline_stage_config_003",
      "sample_idx": 2
    },
    {
      "blind_id": "BRV-79A25AE4",
      "benchmark": "pipeline_stage_config",
      "sample_name": "pipeline_stage_config_009",
      "sample_idx": 8
    },
    {
      "blind_id": "BRV-7DA56FB6",
      "benchmark": "pipeline_stage_config",
      "sample_name": "pipeline_stage_config_012",
      "sample_idx": 11
    },
    {
      "blind_id": "BRV-873FA473",
      "benchmark": "pipeline_stage_config",
      "sample_name": "pipeline_stage_config_014",
      "sample_idx": 13
    },
    {
      "blind_id": "BRV-88B13933",
      "benchmark": "pipeline_stage_config",
      "sample_name": "pipeline_stage_config_021",
      "sample_idx": 20
    },
    {
      "blind_id": "BRV-8AC4C77C",
      "benchmark": "pipeline_stage_config",
      "sample_name": "pipeline_stage_config_026",
      "sample_idx": 25
    },
    {
      "blind_id": "BRV-8EC4BC47",
      "benchmark": "pipeline_stage_config",
      "sample_name": "pipeline_stage_config_047",
      "sample_idx": 46
    },
    {
      "blind_id": "BRV-929E82F2",
      "benchmark": "pipeline_stage_config",
      "sample_name": "pipeline_stage_config_066",
      "sample_idx": 65
    },
    {
      "blind_id": "BRV-93FA3858",
      "benchmark": "pipeline_stage_config",
      "sample_name": "pipeline_stage_config_068",
      "sample_idx": 67
    },
    {
      "blind_id": "BRV-9860EEF2",
      "benchmark": "pipeline_stage_config",
      "sample_name": "pipeline_stage_config_079",
      "sample_idx": 78
    },
    {
      "blind_id": "BRV-9BCAE8AE",
      "benchmark": "complex_nested_config",
      "sample_name": "complex_nested_config_005",
      "sample_idx": 4
    },
    {
      "blind_id": "BRV-9DBC585B",
      "benchmark": "complex_nested_config",
      "sample_name": "complex_nested_config_009",
      "sample_idx": 8
    },
    {
      "blind_id": "BRV-9FF0E1DA",
      "benchmark": "complex_nested_config",
      "sample_name": "complex_nested_config_019",
      "sample_idx": 18
    },
    {
      "blind_id": "BRV-A806DB20",
      "benchmark": "complex_nested_config",
      "sample_name": "complex_nested_config_025",
      "sample_idx": 24
    },
    {
      "blind_id": "BRV-AB147B1D",
      "benchmark": "complex_nested_config",
      "sample_name": "complex_nested_config_032",
      "sample_idx": 31
    },
    {
      "blind_id": "BRV-ADD07C68",
      "benchmark": "complex_nested_config",
      "sample_name": "complex_nested_config_037",
      "sample_idx": 36
    },
    {
      "blind_id": "BRV-B2D13875",
      "benchmark": "complex_nested_config",
      "sample_name": "complex_nested_config_046",
      "sample_idx": 45
    },
    {
      "blind_id": "BRV-B9250D5C",
      "benchmark": "complex_nested_config",
      "sample_name": "complex_nested_config_047",
      "sample_idx": 46
    },
    {
      "blind_id": "BRV-C5C2B8BD",
      "benchmark": "complex_nested_config",
      "sample_name": "complex_nested_config_053",
      "sample_idx": 52
    },
    {
      "blind_id": "BRV-CC442C4B",
      "benchmark": "complex_nested_config",
      "sample_name": "complex_nested_config_054",
      "sample_idx": 53
    },
    {
      "blind_id": "BRV-D3A55609",
      "benchmark": "rich_cli_option_groups",
      "sample_name": "rich_cli_option_groups_001",
      "sample_idx": 0
    },
    {
      "blind_id": "BRV-D8A1EACC",
      "benchmark": "rich_cli_option_groups",
      "sample_name": "rich_cli_option_groups_006",
      "sample_idx": 5
    },
    {
      "blind_id": "BRV-DD82BFD0",
      "benchmark": "rich_cli_option_groups",
      "sample_name": "rich_cli_option_groups_008",
      "sample_idx": 7
    },
    {
      "blind_id": "BRV-E26C7C7E",
      "benchmark": "rich_cli_option_groups",
      "sample_name": "rich_cli_option_groups_013",
      "sample_idx": 12
    },
    {
      "blind_id": "BRV-E6783297",
      "benchmark": "rich_cli_option_groups",
      "sample_name": "rich_cli_option_groups_015",
      "sample_idx": 14
    },
    {
      "blind_id": "BRV-EAA314F8",
      "benchmark": "rich_cli_option_groups",
      "sample_name": "rich_cli_option_groups_027",
      "sample_idx": 26
    },
    {
      "blind_id": "BRV-EB40B2E8",
      "benchmark": "rich_cli_option_groups",
      "sample_name": "rich_cli_option_groups_028",
      "sample_idx": 27
    },
    {
      "blind_id": "BRV-F24F9EAD",
      "benchmark": "rich_cli_option_groups",
      "sample_name": "rich_cli_option_groups_045",
      "sample_idx": 44
    },
    {
      "blind_id": "BRV-F42FD14D",
      "benchmark": "rich_cli_option_groups",
      "sample_name": "rich_cli_option_groups_056",
      "sample_idx": 55
    },
    {
      "blind_id": "BRV-FBDEC839",
      "benchmark": "rich_cli_option_groups",
      "sample_name": "rich_cli_option_groups_066",
      "sample_idx": 65
    }
  ],
  "other_missing": []
}