[
  {
    "name": "openmmlab_config_real_001",
    "sp": 1.387,
    "tps": 46.95,
    "wall": 5.772,
    "gen_len": 271,
    "accept": 0,
    "repair": 0,
    "guard_trig": 0,
    "trim": 0,
    "fb_count": 0,
    "fb_tokens": 0,
    "text": "  # 1/4\n    dict(type='LoadAnnotations', with_bbox=True),\n    dict(\n        type='PackDetInputs',\n        meta_keys=('img_id', 'img_path', 'ori_shape', 'img_shape',\n                   'scale_factor'))\n]\n\ntrain_dataloader = dict(\n    batch_size=2,\n    num_workers=2,\n    persistent_workers=True,\n    sampler=dict(type='DefaultSampler', shuffle=True),\n    batch_sampler=dict(type='AspectRatioBatchSampler'),\n    dataset=dict(\n        type='CocoDataset',\n        data_root=data_root,\n        ann_file='annotations/instances_train2017.json',\n        data_prefix=dict(img='train2017/'),\n        filter_cfg=dict(filter_empty_gt=True, min_size=32),\n        pipeline=test_pipeline))\n\nval_dataloader = dict(\n    batch_size=1,\n    num_workers=2,\n    persistent_workers=True,\n    drop_last=False,\n    sampler=dict(type='DefaultSampler', shuffle=False),\n    dataset=dict(\n        type='CocoDataset',\n        data_root=data_root,\n        ann_file='annotations/instances_val2017.json',\n        data_prefix=dict(img='val2017/'),\n        test_mode=True,\n        pipeline=test_pipeline))\n\ntest_dataloader = val_dataloader\n\nval_evaluator = dict(\n    type='",
    "structural_char_recall": 1.0,
    "structural_char_precision": 1.0,
    "structural_char_f1": 1.0,
    "bracket_balance_score": 0.0,
    "structural_validity": 0.0,
    "structure_type_preservation": 1.0,
    "no_repetition_score": 1.0,
    "off_structure_rate": 0.0,
    "repetition_rate": 0.0,
    "is_truncated": 1.0,
    "composite_sq": 0.7
  },
  {
    "name": "openmmlab_config_real_002",
    "sp": 0.663,
    "tps": 21.25,
    "wall": 12.328,
    "gen_len": 262,
    "accept": 0,
    "repair": 0,
    "guard_trig": 0,
    "trim": 0,
    "fb_count": 0,
    "fb_tokens": 0,
    "text": "  # 是否在dataloader的生命周期内保持worker进程持续运行\n    pin_memory=True,  # 是否在数据加载到GPU时将数据固定在内存中\n    drop_last=False,  # 是否丢弃最后一个数据batch\n    sampler=dict(type='DefaultSampler', shuffle=False),  # 采样器类型\n    dataset=dict(\n        type='BasicDataset',\n        data_root='data/imagenet',\n        data_prefix='val',\n        ann_file='meta/val.txt',\n        pipeline=[\n            dict(type='LoadImageFromFile'),\n            dict(type='Resize', scale=(224, 224), interpolation='bicubic'),\n            dict(\n                type='PackInputs',\n                meta_keys=('sample_idx', 'img_path', 'ori_shape', 'img_shape',\n                           'scale_factor', 'flip', 'flip_direction'))\n        ]))  # 数据集类型和数据预处理管道\ntrain_dataloader = dict(\n    batch_size=32,\n    num_workers=2,\n    persistent_workers=True,\n    pin_memory=True,\n    drop_last=True,\n    sampler=dict(type='DefaultSampler', shuffle=True),\n    dataset=dict(\n        type='BasicDataset',\n        data_root='data/imagenet',\n        data_prefix='train',\n        ann",
    "structural_char_recall": 1.0,
    "structural_char_precision": 0.9817,
    "structural_char_f1": 0.9907,
    "bracket_balance_score": 0.0,
    "structural_validity": 0.0,
    "structure_type_preservation": 1.0,
    "no_repetition_score": 1.0,
    "off_structure_rate": 0.0,
    "repetition_rate": 0.0,
    "is_truncated": 1.0,
    "composite_sq": 0.6963
  },
  {
    "name": "openmmlab_config_real_003",
    "sp": 1.609,
    "tps": 50.17,
    "wall": 5.401,
    "gen_len": 271,
    "accept": 0,
    "repair": 0,
    "guard_trig": 0,
    "trim": 0,
    "fb_count": 0,
    "fb_tokens": 0,
    "text": "  # 1/4\n    dict(type='LoadAnnotations', with_bbox=True),\n    dict(\n        type='PackDetInputs',\n        meta_keys=('img_id', 'img_path', 'ori_shape', 'img_shape',\n                   'scale_factor'))\n]\n\ntrain_dataloader = dict(\n    batch_size=2,\n    num_workers=2,\n    persistent_workers=True,\n    sampler=dict(type='DefaultSampler', shuffle=True),\n    batch_sampler=dict(type='AspectRatioBatchSampler'),\n    dataset=dict(\n        type='CocoDataset',\n        data_root=data_root,\n        ann_file='annotations/instances_train2017.json',\n        data_prefix=dict(img='train2017/'),\n        filter_cfg=dict(filter_empty_gt=True, min_size=32),\n        pipeline=test_pipeline))\n\nval_dataloader = dict(\n    batch_size=1,\n    num_workers=2,\n    persistent_workers=True,\n    drop_last=False,\n    sampler=dict(type='DefaultSampler', shuffle=False),\n    dataset=dict(\n        type='CocoDataset',\n        data_root=data_root,\n        ann_file='annotations/instances_val2017.json',\n        data_prefix=dict(img='val2017/'),\n        test_mode=True,\n        pipeline=test_pipeline))\n\ntest_dataloader = val_dataloader\n\nval_evaluator = dict(\n    type='",
    "structural_char_recall": 1.0,
    "structural_char_precision": 1.0,
    "structural_char_f1": 1.0,
    "bracket_balance_score": 0.0,
    "structural_validity": 0.0,
    "structure_type_preservation": 1.0,
    "no_repetition_score": 1.0,
    "off_structure_rate": 0.0,
    "repetition_rate": 0.0,
    "is_truncated": 1.0,
    "composite_sq": 0.7
  },
  {
    "name": "openmmlab_config_real_004",
    "sp": 1.261,
    "tps": 39.24,
    "wall": 6.907,
    "gen_len": 271,
    "accept": 0,
    "repair": 0,
    "guard_trig": 0,
    "trim": 0,
    "fb_count": 0,
    "fb_tokens": 0,
    "text": "  # True,\n    pin_memory=True,\n    drop_last=False,\n    sampler=dict(type='DefaultSampler', shuffle=False),\n    dataset=dict(\n        type='BasicDataset',\n        data_root='data/val',\n        data_prefix='.',\n        pipeline=[\n            dict(type='LoadImage'),\n            dict(type='Resize', scale=(256, 256)),\n            dict(type='PackInputs')\n        ],\n        metainfo=dict(dataset_type='val', classes=['0', '1', '2', '3', '4', '5', '6', '7', '8', '9', '10', '11', '12', '13', '14', '15', '16', '17', '18', '19', '20', '21', '22', '23', '24', '25', '26', '27', '28', '29', '30', '31', '32', '33', '34', '35', '36', '37', '38', '39', '40', '41', '42', '43', '44', '45', '4",
    "structural_char_recall": 1.0,
    "structural_char_precision": 0.9714,
    "structural_char_f1": 0.9855,
    "bracket_balance_score": 0.0,
    "structural_validity": 0.0,
    "structure_type_preservation": 1.0,
    "no_repetition_score": 1.0,
    "off_structure_rate": 0.0,
    "repetition_rate": 0.0,
    "is_truncated": 1.0,
    "composite_sq": 0.6942
  },
  {
    "name": "openmmlab_config_real_005",
    "sp": 1.294,
    "tps": 39.89,
    "wall": 6.467,
    "gen_len": 258,
    "accept": 0,
    "repair": 0,
    "guard_trig": 0,
    "trim": 0,
    "fb_count": 0,
    "fb_tokens": 0,
    "text": "  # add loading annotation\n        type='LoadAnnotations',\n        with_bbox=True,\n        with_mask=True,\n        with_seg=True,\n        backend_args=backend_args),\n    dict(\n        type='PackDetInputs',\n        meta_keys=('img_id', 'img_path', 'ori_shape', 'img_shape',\n                   'scale_factor'))\n]\n\ntrain_dataloader = dict(\n    batch_size=2,\n    num_workers=2,\n    persistent_workers=True,\n    sampler=dict(type='DefaultSampler', shuffle=True),\n    dataset=dict(\n        type='CocoDataset',\n        data_root=data_root,\n        ann_file='annotations/instances_train2017.json',\n        data_prefix=dict(img='train2017/'),\n        filter_cfg=dict(filter_empty_gt=True, min_size=32),\n        pipeline=[\n            dict(type='LoadImageFromFile', backend_args=backend_args),\n            dict(type='LoadAnnotations', with_bbox=True, with_mask=True),\n            dict(\n                type='RandomResize',\n                scale=(2048, 512),\n                ratio_range=(0.1, 2.0),\n                keep_ratio=True),\n            dict(\n                type='RandomCrop',\n                crop_size=(512, 512),\n                re",
    "structural_char_recall": 1.0,
    "structural_char_precision": 0.9924,
    "structural_char_f1": 0.9962,
    "bracket_balance_score": 0.0,
    "structural_validity": 0.0,
    "structure_type_preservation": 1.0,
    "no_repetition_score": 1.0,
    "off_structure_rate": 0.0,
    "repetition_rate": 0.0,
    "is_truncated": 1.0,
    "composite_sq": 0.6985
  },
  {
    "name": "openmmlab_config_real_006",
    "sp": 0.748,
    "tps": 23.33,
    "wall": 11.229,
    "gen_len": 262,
    "accept": 0,
    "repair": 0,
    "guard_trig": 0,
    "trim": 0,
    "fb_count": 0,
    "fb_tokens": 0,
    "text": "  # 是否在dataloader的生命周期内保持worker进程持续运行\n    pin_memory=True,  # 是否在数据加载到GPU时将数据固定在内存中\n    drop_last=False,  # 是否丢弃最后一个数据batch\n    sampler=dict(type='DefaultSampler', shuffle=False),  # 采样器类型\n    dataset=dict(\n        type='BasicDataset',\n        data_root='data/imagenet',\n        data_prefix='val',\n        ann_file='meta/val.txt',\n        pipeline=[\n            dict(type='LoadImageFromFile'),\n            dict(type='Resize', scale=(224, 224), interpolation='bicubic'),\n            dict(\n                type='PackInputs',\n                meta_keys=('sample_idx', 'img_path', 'ori_shape', 'img_shape',\n                           'scale_factor', 'flip', 'flip_direction'))\n        ]))  # 数据集类型和数据预处理管道\ntrain_dataloader = dict(\n    batch_size=32,\n    num_workers=2,\n    persistent_workers=True,\n    pin_memory=True,\n    drop_last=True,\n    sampler=dict(type='DefaultSampler', shuffle=True),\n    dataset=dict(\n        type='BasicDataset',\n        data_root='data/imagenet',\n        data_prefix='train',\n        ann",
    "structural_char_recall": 1.0,
    "structural_char_precision": 0.9817,
    "structural_char_f1": 0.9907,
    "bracket_balance_score": 0.0,
    "structural_validity": 0.0,
    "structure_type_preservation": 1.0,
    "no_repetition_score": 1.0,
    "off_structure_rate": 0.0,
    "repetition_rate": 0.0,
    "is_truncated": 1.0,
    "composite_sq": 0.6963
  },
  {
    "name": "openmmlab_config_real_007",
    "sp": 2.257,
    "tps": 72.67,
    "wall": 3.674,
    "gen_len": 267,
    "accept": 0,
    "repair": 0,
    "guard_trig": 0,
    "trim": 0,
    "fb_count": 0,
    "fb_tokens": 0,
    "text": "  # 加载bbox\n    dict(type='Resize', scale=(1333, 800), keep_ratio=True),\n    dict(type='RandomFlip', prob=0.5),\n    dict(type='PackDetInputs')\n]\nval_pipeline = [\n    dict(type='LoadImageFromFile', backend_args=backend_args),\n    dict(type='Resize', scale=(1333, 800), keep_ratio=True),\n    dict(type='LoadAnnotations', with_bbox=True),  # 加载bbox\n    dict(\n        type='PackDetInputs',\n        meta_keys=('img_id', 'img_path', 'ori_shape', 'img_shape',\n                   'scale_factor'))\n]\ntest_pipeline = [\n    dict(type='LoadImageFromFile', backend_args=backend_args),\n    dict(type='Resize', scale=(1333, 800), keep_ratio=True),\n    dict(type='LoadAnnotations', with_bbox=True),  # 加载bbox\n    dict(\n        type='PackDetInputs',\n        meta_keys=('img_id', 'img_path', 'ori_shape', 'img_shape',\n                   'scale_factor'))\n]\ntrain_dataloader = dict(\n    batch_size=2,\n    num_workers=2,\n    persistent_workers=True,\n    sampler=dict(type='DefaultSampler', shuffle=True",
    "structural_char_recall": 1.0,
    "structural_char_precision": 1.0,
    "structural_char_f1": 1.0,
    "bracket_balance_score": 0.0,
    "structural_validity": 0.0,
    "structure_type_preservation": 1.0,
    "no_repetition_score": 0.4,
    "off_structure_rate": 0.0,
    "repetition_rate": 0.2,
    "is_truncated": 1.0,
    "composite_sq": 0.64
  },
  {
    "name": "openmmlab_config_real_008",
    "sp": 0.925,
    "tps": 30.28,
    "wall": 8.654,
    "gen_len": 262,
    "accept": 0,
    "repair": 0,
    "guard_trig": 0,
    "trim": 0,
    "fb_count": 0,
    "fb_tokens": 0,
    "text": "  # 2048, 1024\n    dict(type='LoadAnnotations'),\n    dict(\n        type='PackSegInputs',\n        meta_keys=('img_path', 'img_shape', 'ori_shape', 'img_shape',\n                   'scale_factor'))\n]\n\nval_dataloader = dict(\n    batch_size=1,\n    num_workers=4,\n    persistent_workers=True,\n    drop_last=False,\n    sampler=dict(type='DefaultSampler', shuffle=False),\n    dataset=dict(\n        type='ADE20KDataset',\n        data_root='data/ADEChallengeData2016',\n        data_prefix=dict(img_path='images/validation', seg_map_path='annotations/validation'),\n        pipeline=test_pipeline,\n        backend_args=backend_args))\n\nval_evaluator = dict(type='IoUMetric', iou_metrics=['mIoU'])\ntest_dataloader = val_dataloader\ntest_evaluator = val_evaluator\n\n# 模型\nmodel = dict(\n    type='EncoderDecoder',\n    data_preprocessor=dict(\n        type='SegDataPreProcessor',\n        mean=[123.675, 116.28, 103.53],\n        std=[58.395, 57.12, 57",
    "structural_char_recall": 1.0,
    "structural_char_precision": 0.973,
    "structural_char_f1": 0.9863,
    "bracket_balance_score": 0.0,
    "structural_validity": 0.0,
    "structure_type_preservation": 1.0,
    "no_repetition_score": 1.0,
    "off_structure_rate": 0.0,
    "repetition_rate": 0.0,
    "is_truncated": 1.0,
    "composite_sq": 0.6945
  },
  {
    "name": "openmmlab_config_real_009",
    "sp": 1.652,
    "tps": 56.58,
    "wall": 4.772,
    "gen_len": 270,
    "accept": 0,
    "repair": 0,
    "guard_trig": 0,
    "trim": 0,
    "fb_count": 0,
    "fb_tokens": 0,
    "text": "  # shuffle=True\n    dataset=dict(\n        type='CocoDataset',\n        data_root=data_root,\n        ann_file='annotations/instances_train2017.json',\n        data_prefix=dict(img='train2017/'),\n        filter_cfg=dict(filter_empty_gt=True, min_size=32),\n        pipeline=[\n            dict(type='LoadImageFromFile', to_float32=True),\n            dict(type='LoadAnnotations', with_bbox=True, with_mask=True),\n            dict(\n                type='RandomChoiceResize',\n                scales=[(1333, 640), (1333, 672), (1333, 704), (1333, 736),\n                        (1333, 768), (1333, 800)],\n                keep_ratio=True),\n            dict(type='RandomFlip', prob=0.5),\n            dict(type='PackDetInputs')\n        ]))\nval_dataloader = dict(\n    batch_size=1,\n    num_workers=2,\n    persistent_workers=True,\n    sampler=dict(type='DefaultSampler', shuffle=False),\n    dataset=dict(\n        type='CocoDataset',\n        data_root=data_root,\n        ann_file='annotations/instances_val2017.json',\n",
    "structural_char_recall": 1.0,
    "structural_char_precision": 0.9697,
    "structural_char_f1": 0.9846,
    "bracket_balance_score": 0.0,
    "structural_validity": 0.3,
    "structure_type_preservation": 1.0,
    "no_repetition_score": 1.0,
    "off_structure_rate": 0.0,
    "repetition_rate": 0.0,
    "is_truncated": 0.0,
    "composite_sq": 0.6938
  },
  {
    "name": "openmmlab_config_real_010",
    "sp": 0.672,
    "tps": 22.73,
    "wall": 11.702,
    "gen_len": 266,
    "accept": 0,
    "repair": 0,
    "guard_trig": 0,
    "trim": 0,
    "fb_count": 0,
    "fb_tokens": 0,
    "text": "  # set to True to drop the last incomplete batch\n    collate_fn=dict(type='default_collate'),\n    dataset=dict(\n        type='CocoDataset',\n        data_root='data/coco/',\n        ann_file='annotations/instances_val2017.json',\n        data_prefix=dict(img='val2017/'),\n        test_mode=True,\n        batch_shapes_cfg=dict(\n            type='BatchShapePolicy',\n            img_size=(1024, 1024),\n            partition_type='fixed_sized',\n            batched_size=1,\n            extra_pad_ratio=0.1,\n            divisor=32,\n            max_num_items=500),\n        pipeline=[\n            dict(type='LoadImageFromFile', backend_args=None),\n            dict(type='LoadAnnotations', with_bbox=True, with_mask=True),\n            dict(\n                type='PackDetInputs',\n                meta_keys=('img_id', 'img_path', 'ori_shape', 'img_shape',\n                           'scale_factor'))\n        ]))  # yapf: disable\n这段代码是做什么的\n这段代码定义了一个数据加载器（`val_dataloader`），用于COCO数据集的验证阶段。具体来说，它包含了以下几个关键部分：\n\n1. **数据加载器配置**：\n   - `",
    "structural_char_recall": 1.0,
    "structural_char_precision": 0.9697,
    "structural_char_f1": 0.9846,
    "bracket_balance_score": 0.0,
    "structural_validity": 0.0,
    "structure_type_preservation": 1.0,
    "no_repetition_score": 1.0,
    "off_structure_rate": 0.0,
    "repetition_rate": 0.0,
    "is_truncated": 1.0,
    "composite_sq": 0.6938
  },
  {
    "name": "openmmlab_config_real_011",
    "sp": 1.625,
    "tps": 55.01,
    "wall": 4.745,
    "gen_len": 261,
    "accept": 0,
    "repair": 0,
    "guard_trig": 0,
    "trim": 0,
    "fb_count": 0,
    "fb_tokens": 0,
    "text": "  # with_mask=True\n    dict(type='Resize', scale=(1333, 800), keep_ratio=True),\n    dict(type='RandomFlip', prob=0.5),\n    dict(type='PackDetInputs')\n]\ntest_pipeline = [\n    dict(type='LoadImageFromFile', backend_args=backend_args),\n    dict(type='Resize', scale=(1333, 800), keep_ratio=True),\n    dict(type='LoadAnnotations', with_bbox=True, with_mask=True),\n    dict(\n        type='PackDetInputs',\n        meta_keys=('img_id', 'img_path', 'ori_shape', 'img_shape',\n                   'scale_factor'))\n]\ntrain_dataloader = dict(\n    batch_size=2,\n    num_workers=2,\n    persistent_workers=True,\n    sampler=dict(type='DefaultSampler', shuffle=True),\n    batch_sampler=dict(type='AspectRatioBatchSampler'),\n    dataset=dict(\n        type='CocoDataset',\n        data_root=data_root,\n        ann_file='annotations/instances_train2017.json',\n        data_prefix=dict(img='train2017/'),\n        filter_cfg=dict(filter_empty_gt=True, min_size=32),\n        pipeline=train_pipeline))\nval_dataloader = dict(\n    batch_size=1,\n   ",
    "structural_char_recall": 1.0,
    "structural_char_precision": 1.0,
    "structural_char_f1": 1.0,
    "bracket_balance_score": 0.0,
    "structural_validity": 0.3,
    "structure_type_preservation": 1.0,
    "no_repetition_score": 1.0,
    "off_structure_rate": 0.0,
    "repetition_rate": 0.0,
    "is_truncated": 0.0,
    "composite_sq": 0.7
  },
  {
    "name": "openmmlab_config_real_012",
    "sp": 0.914,
    "tps": 30.58,
    "wall": 8.569,
    "gen_len": 262,
    "accept": 0,
    "repair": 0,
    "guard_trig": 0,
    "trim": 0,
    "fb_count": 0,
    "fb_tokens": 0,
    "text": "  # 2048, 1024\n    dict(type='LoadAnnotations'),\n    dict(\n        type='PackSegInputs',\n        meta_keys=('img_path', 'img_shape', 'ori_shape', 'img_shape',\n                   'scale_factor'))\n]\n\nval_dataloader = dict(\n    batch_size=1,\n    num_workers=4,\n    persistent_workers=True,\n    drop_last=False,\n    sampler=dict(type='DefaultSampler', shuffle=False),\n    dataset=dict(\n        type='ADE20KDataset',\n        data_root='data/ADEChallengeData2016',\n        data_prefix=dict(img_path='images/validation', seg_map_path='annotations/validation'),\n        pipeline=test_pipeline,\n        backend_args=backend_args))\n\nval_evaluator = dict(type='IoUMetric', iou_metrics=['mIoU'])\ntest_dataloader = val_dataloader\ntest_evaluator = val_evaluator\n\n# 模型\nmodel = dict(\n    type='EncoderDecoder',\n    data_preprocessor=dict(\n        type='SegDataPreProcessor',\n        mean=[123.675, 116.28, 103.53],\n        std=[58.395, 57.12, 57",
    "structural_char_recall": 1.0,
    "structural_char_precision": 0.973,
    "structural_char_f1": 0.9863,
    "bracket_balance_score": 0.0,
    "structural_validity": 0.0,
    "structure_type_preservation": 1.0,
    "no_repetition_score": 1.0,
    "off_structure_rate": 0.0,
    "repetition_rate": 0.0,
    "is_truncated": 1.0,
    "composite_sq": 0.6945
  },
  {
    "name": "openmmlab_config_real_013",
    "sp": 1.63,
    "tps": 55.29,
    "wall": 4.884,
    "gen_len": 270,
    "accept": 0,
    "repair": 0,
    "guard_trig": 0,
    "trim": 0,
    "fb_count": 0,
    "fb_tokens": 0,
    "text": "  # shuffle=True\n    dataset=dict(\n        type='CocoDataset',\n        data_root=data_root,\n        ann_file='annotations/instances_train2017.json',\n        data_prefix=dict(img='train2017/'),\n        filter_cfg=dict(filter_empty_gt=True, min_size=32),\n        pipeline=[\n            dict(type='LoadImageFromFile', to_float32=True),\n            dict(type='LoadAnnotations', with_bbox=True, with_mask=True),\n            dict(\n                type='RandomChoiceResize',\n                scales=[(1333, 640), (1333, 672), (1333, 704), (1333, 736),\n                        (1333, 768), (1333, 800)],\n                keep_ratio=True),\n            dict(type='RandomFlip', prob=0.5),\n            dict(type='PackDetInputs')\n        ]))\nval_dataloader = dict(\n    batch_size=1,\n    num_workers=2,\n    persistent_workers=True,\n    sampler=dict(type='DefaultSampler', shuffle=False),\n    dataset=dict(\n        type='CocoDataset',\n        data_root=data_root,\n        ann_file='annotations/instances_val2017.json',\n",
    "structural_char_recall": 1.0,
    "structural_char_precision": 0.9697,
    "structural_char_f1": 0.9846,
    "bracket_balance_score": 0.0,
    "structural_validity": 0.3,
    "structure_type_preservation": 1.0,
    "no_repetition_score": 1.0,
    "off_structure_rate": 0.0,
    "repetition_rate": 0.0,
    "is_truncated": 0.0,
    "composite_sq": 0.6938
  },
  {
    "name": "openmmlab_config_real_014",
    "sp": 0.673,
    "tps": 22.9,
    "wall": 11.614,
    "gen_len": 266,
    "accept": 0,
    "repair": 0,
    "guard_trig": 0,
    "trim": 0,
    "fb_count": 0,
    "fb_tokens": 0,
    "text": "  # set to True to drop the last incomplete batch\n    collate_fn=dict(type='default_collate'),\n    dataset=dict(\n        type='CocoDataset',\n        data_root='data/coco/',\n        ann_file='annotations/instances_val2017.json',\n        data_prefix=dict(img='val2017/'),\n        test_mode=True,\n        batch_shapes_cfg=dict(\n            type='BatchShapePolicy',\n            img_size=(1024, 1024),\n            partition_type='fixed_sized',\n            batched_size=1,\n            extra_pad_ratio=0.1,\n            divisor=32,\n            max_num_items=500),\n        pipeline=[\n            dict(type='LoadImageFromFile', backend_args=None),\n            dict(type='LoadAnnotations', with_bbox=True, with_mask=True),\n            dict(\n                type='PackDetInputs',\n                meta_keys=('img_id', 'img_path', 'ori_shape', 'img_shape',\n                           'scale_factor'))\n        ]))  # yapf: disable\n这段代码是做什么的\n这段代码定义了一个数据加载器（`val_dataloader`），用于COCO数据集的验证阶段。具体来说，它包含了以下几个关键部分：\n\n1. **数据加载器配置**：\n   - `",
    "structural_char_recall": 1.0,
    "structural_char_precision": 0.9697,
    "structural_char_f1": 0.9846,
    "bracket_balance_score": 0.0,
    "structural_validity": 0.0,
    "structure_type_preservation": 1.0,
    "no_repetition_score": 1.0,
    "off_structure_rate": 0.0,
    "repetition_rate": 0.0,
    "is_truncated": 1.0,
    "composite_sq": 0.6938
  },
  {
    "name": "openmmlab_config_real_015",
    "sp": 1.931,
    "tps": 65.1,
    "wall": 3.963,
    "gen_len": 258,
    "accept": 0,
    "repair": 0,
    "guard_trig": 0,
    "trim": 0,
    "fb_count": 0,
    "fb_tokens": 0,
    "text": " # 'cv2' or 'pillow'\n        to_float32=True),\n    dict(\n        type='MultiScaleFlipAug',\n        img_scale=(1333, 800),\n        flip=False,\n        transforms=[\n            dict(type='Resize', keep_ratio=True),\n            dict(type='RandomFlip'),\n            dict(type='Normalize', **img_norm_cfg),\n            dict(type='Pad', size_divisor=32),\n            dict(type='ImageToTensor', keys=['img']),\n            dict(type='Collect', keys=['img']),\n        ])\n]\n\ndata = dict(\n    samples_per_gpu=2,\n    workers_per_gpu=2,\n    train=dict(\n        type='CocoDataset',\n        ann_file='data/coco/annotations/instances_train2017.json',\n        img_prefix='data/coco/train2017/',\n        pipeline=train_pipeline),\n    val=dict(\n        type='CocoDataset',\n        ann_file='data/coco/annotations/instances_val2017.json',\n        img_prefix='data/coco/val2017/',\n        pipeline=test_pipeline),\n    test=dict(\n        type='CocoDataset',\n        ann_file='data/coco/annotations/instances_val2017.json',\n       ",
    "structural_char_recall": 1.0,
    "structural_char_precision": 1.0,
    "structural_char_f1": 1.0,
    "bracket_balance_score": 0.0,
    "structural_validity": 0.3,
    "structure_type_preservation": 1.0,
    "no_repetition_score": 1.0,
    "off_structure_rate": 0.0,
    "repetition_rate": 0.0,
    "is_truncated": 0.0,
    "composite_sq": 0.7
  },
  {
    "name": "openmmlab_config_real_016",
    "sp": 0.628,
    "tps": 21.47,
    "wall": 12.205,
    "gen_len": 262,
    "accept": 0,
    "repair": 0,
    "guard_trig": 0,
    "trim": 0,
    "fb_count": 0,
    "fb_tokens": 0,
    "text": "  # 是否在dataloader的生命周期内保持worker进程持续运行\n    pin_memory=True,  # 是否在数据加载到GPU时将数据固定在内存中\n    drop_last=False,  # 是否丢弃最后一个数据batch\n    sampler=dict(type='DefaultSampler', shuffle=False),  # 采样器类型\n    dataset=dict(\n        type='BasicDataset',\n        data_root='data/imagenet',\n        data_prefix='val',\n        ann_file='meta/val.txt',\n        pipeline=[\n            dict(type='LoadImageFromFile'),\n            dict(type='Resize', scale=(224, 224), interpolation='bicubic'),\n            dict(\n                type='PackInputs',\n                meta_keys=('sample_idx', 'img_path', 'ori_shape', 'img_shape',\n                           'scale_factor', 'flip', 'flip_direction'))\n        ]))  # 数据集类型和数据预处理管道\ntrain_dataloader = dict(\n    batch_size=32,\n    num_workers=2,\n    persistent_workers=True,\n    pin_memory=True,\n    drop_last=True,\n    sampler=dict(type='DefaultSampler', shuffle=True),\n    dataset=dict(\n        type='BasicDataset',\n        data_root='data/imagenet',\n        data_prefix='train',\n        ann",
    "structural_char_recall": 1.0,
    "structural_char_precision": 0.9817,
    "structural_char_f1": 0.9907,
    "bracket_balance_score": 0.0,
    "structural_validity": 0.0,
    "structure_type_preservation": 1.0,
    "no_repetition_score": 1.0,
    "off_structure_rate": 0.0,
    "repetition_rate": 0.0,
    "is_truncated": 1.0,
    "composite_sq": 0.6963
  },
  {
    "name": "openmmlab_config_real_017",
    "sp": 1.258,
    "tps": 41.0,
    "wall": 6.244,
    "gen_len": 256,
    "accept": 0,
    "repair": 0,
    "guard_trig": 0,
    "trim": 0,
    "fb_count": 0,
    "fb_tokens": 0,
    "text": " # resize\n        type='RandomResize',\n        scale=(1024, 1024),\n        ratio_range=(0.5, 2.0),\n        keep_ratio=True),\n    dict(type='RandomCrop', crop_size=(1024, 1024), cat_max_ratio=0.75),\n    dict(type='RandomFlip', prob=0.5),\n    dict(type='PhotoMetricDistortion'),\n    dict(type='PackSegInputs')\n]\n\ntest_pipeline = [\n    dict(type='LoadImageFromFile'),\n    dict(type='Resize', scale=(1024, 1024), keep_ratio=True),\n    # add loading annotation after ``Resize`` because ground truth\n    # does not need to do resize data transform\n    dict(type='LoadAnnotations'),\n    dict(type='PackSegInputs')\n]\n\ntrain_dataloader = dict(\n    batch_size=4,\n    num_workers=4,\n    persistent_workers=True,\n    sampler=dict(type='InfiniteSampler', shuffle=True),\n    dataset=dict(\n        type='RepeatDataset',\n        times=3,\n        dataset=dict(\n            type='ADE20KDataset',\n            data_root='data/ade20k',\n            data_prefix='images",
    "structural_char_recall": 1.0,
    "structural_char_precision": 0.9919,
    "structural_char_f1": 0.996,
    "bracket_balance_score": 0.0,
    "structural_validity": 0.0,
    "structure_type_preservation": 1.0,
    "no_repetition_score": 1.0,
    "off_structure_rate": 0.0,
    "repetition_rate": 0.0,
    "is_truncated": 1.0,
    "composite_sq": 0.6984
  },
  {
    "name": "openmmlab_config_real_018",
    "sp": 2.007,
    "tps": 68.35,
    "wall": 3.906,
    "gen_len": 267,
    "accept": 0,
    "repair": 0,
    "guard_trig": 0,
    "trim": 0,
    "fb_count": 0,
    "fb_tokens": 0,
    "text": "  # (2048, 512)\n    dict(type='LoadAnnotations'),\n    dict(\n        type='PackSegInputs',\n        meta_keys=('img_path', 'img_shape', 'ori_shape', 'img_shape',\n                   'scale_factor', 'flip', 'flip_direction'))\n]\n\nval_pipeline = [\n    dict(type='LoadImageFromFile'),\n    dict(type='Resize', scale=(2048, 512), keep_ratio=True),  # (2048, 512)\n    dict(type='LoadAnnotations'),\n    dict(\n        type='PackSegInputs',\n        meta_keys=('img_path', 'img_shape', 'ori_shape', 'img_shape',\n                   'scale_factor', 'flip', 'flip_direction'))\n]\n\ntest_pipeline = [\n    dict(type='LoadImageFromFile'),\n    dict(type='Resize', scale=(2048, 512), keep_ratio=True),  # (2048, 512)\n    dict(type='LoadAnnotations'),\n    dict(\n        type='PackSegInputs',\n        meta_keys=('img_path', 'img_shape', 'ori_shape', 'img_shape',\n                   'scale_factor', 'flip', 'flip_direction'))\n]  # (2048, 512)\n\n",
    "structural_char_recall": 1.0,
    "structural_char_precision": 0.9844,
    "structural_char_f1": 0.9921,
    "bracket_balance_score": 0.0,
    "structural_validity": 0.3,
    "structure_type_preservation": 1.0,
    "no_repetition_score": 0.0455,
    "off_structure_rate": 0.0,
    "repetition_rate": 0.3182,
    "is_truncated": 0.0,
    "composite_sq": 0.6014
  },
  {
    "name": "openmmlab_config_real_019",
    "sp": 1.383,
    "tps": 47.11,
    "wall": 5.732,
    "gen_len": 270,
    "accept": 0,
    "repair": 0,
    "guard_trig": 0,
    "trim": 0,
    "fb_count": 0,
    "fb_tokens": 0,
    "text": "  # 4\n    persistent_workers=True,\n    dataset=dict(\n        type='CocoDataset',\n        data_root='data/coco',\n        ann_file='annotations/instances_train2017.json',\n        img_prefix='train2017/',\n        filter_cfg=dict(filter_empty_gt=True, min_size=32),\n        pipeline=[\n            dict(type='LoadImageFromFile'),\n            dict(type='LoadAnnotations', with_bbox=True, with_mask=True),\n            dict(type='Resize', scale=(1333, 800), keep_ratio=True),\n            dict(type='RandomFlip', prob=0.5),\n            dict(\n                type='Normalize',\n                mean=[123.675, 116.28, 103.53],\n                std=[58.395, 57.12, 57.375],\n                to_rgb=True),\n            dict(type='Pad', size_divisor=32),\n            dict(type='DefaultFormatBundle'),\n            dict(type='Collect', keys=['img', 'gt_bboxes', 'gt_labels', 'gt_masks'])\n        ]\n    )\n)\n\ntest_dataloader = dict(\n    batch_size=1,\n    num_workers=4,  # 4\n    persistent_workers=True",
    "structural_char_recall": 1.0,
    "structural_char_precision": 0.9365,
    "structural_char_f1": 0.9672,
    "bracket_balance_score": 0.0,
    "structural_validity": 0.0,
    "structure_type_preservation": 1.0,
    "no_repetition_score": 1.0,
    "off_structure_rate": 0.0,
    "repetition_rate": 0.0,
    "is_truncated": 1.0,
    "composite_sq": 0.6869
  },
  {
    "name": "openmmlab_config_real_020",
    "sp": 0.798,
    "tps": 25.76,
    "wall": 10.055,
    "gen_len": 259,
    "accept": 0,
    "repair": 0,
    "guard_trig": 0,
    "trim": 0,
    "fb_count": 0,
    "fb_tokens": 0,
    "text": "  # 是否在dataloader的生命周期内保持worker进程持续运行\n    pin_memory=True,  # 是否在数据加载到GPU时将数据复制到CUDA设备上\n    drop_last=True,  # 是否在每个epoch结束时丢弃最后一个batch\n    sampler=dict(type='DefaultSampler', shuffle=False),  # 是否在每个epoch结束时丢弃最后一个batch\n    dataset=dict(\n        type='BasicDataset',\n        data_root='data/ade20k',\n        data_prefix='val',\n        pipeline=[\n            dict(type='LoadImageFromFile'),\n            dict(type='LoadAnnotations', reduce_zero_label=True),\n            dict(\n                type='RandomResize',\n                scale=(1024, 1024),\n                ratio_range=(0.5, 2.0),\n                keep_ratio=True),\n            dict(\n                type='RandomCrop',\n                crop_size=(512, 512),\n                cat_max_ratio=0.75),\n            dict(type='RandomFlip', prob=0.5),\n            dict(type='PackSegInputs')\n        ],\n        metainfo=dict(\n            classes=('person', 'bicycle', 'car', 'motorcycle', 'airplane',\n                     'bus', 'train', '",
    "structural_char_recall": 1.0,
    "structural_char_precision": 0.981,
    "structural_char_f1": 0.9904,
    "bracket_balance_score": 0.0,
    "structural_validity": 0.0,
    "structure_type_preservation": 1.0,
    "no_repetition_score": 1.0,
    "off_structure_rate": 0.0,
    "repetition_rate": 0.0,
    "is_truncated": 1.0,
    "composite_sq": 0.6962
  }
]